dawgs_ml/__init__.py
dawgs_ml/models.py
dawgs_ml/preprocess.py
dawgs_ml/dataframe/__init__.py
dawgs_ml/dataframe/dataframe.py
dawgs_ml/utils/__init__.py
dawgs_ml/utils/model_utils.py
dawgs_ml/utils/utils.py
DawgsML-0.0.3.dist-info/LICENSE
DawgsML-0.0.3.dist-info/METADATA
DawgsML-0.0.3.dist-info/WHEEL
DawgsML-0.0.3.dist-info/top_level.txt
DawgsML-0.0.3.dist-info/RECORD
