Metadata-Version: 2.1
Name: DawgsML
Version: 0.0.3
Summary: A simple library for machine learning without a requirements.txt
Home-page: https://github.com/Doriasamp/DawgsML.git
Author: Andrea Marchi
Author-email: andreaphilly@hotmail.com
Project-URL: Source, https://github.com/Doriasamp/DawgsML.git
Keywords: machine learning,data processing,custom data structures,pandas-like,data analysis,ml,data science,statistics,numpy,deep learning,preprocessing,pandas simulation
Classifier: Development Status :: 3 - Alpha
Classifier: Intended Audience :: Developers
Classifier: Topic :: Software Development :: Libraries
Classifier: License :: OSI Approved :: MIT License
Classifier: Programming Language :: Python :: 3
Classifier: Programming Language :: Python :: 3.7
Classifier: Programming Language :: Python :: 3.8
Classifier: Programming Language :: Python :: 3.9
Classifier: Programming Language :: Python :: 3.10
Classifier: Programming Language :: Python :: 3.11
Classifier: Programming Language :: Python :: 3.12
Requires-Python: >=3.9
License-File: LICENSE
